setup.py
jackchendongtest/__init__.py
jackchendongtest/config.py
jackchendongtest/event.py
jackchendongtest/observer.py
jackchendongtest/server.py
jackchendongtest/test.py
jackchendongtest/test2.py
jackchendongtest/util.py
jackchendongtest.egg-info/PKG-INFO
jackchendongtest.egg-info/SOURCES.txt
jackchendongtest.egg-info/dependency_links.txt
jackchendongtest.egg-info/requires.txt
jackchendongtest.egg-info/top_level.txt