Metadata-Version: 2.1
Name: jackchendongtest
Version: 1.1.1
Summary: observa API
Home-page: https://github.com
Author: chendong
Author-email: chendong@qq.com
License: MIT
Keywords: API,AI,Python
Platform: UNKNOWN
Requires-Python: >=3.9
